iotccsdk/__init__.py
iotccsdk/camera.py
iotccsdk/frame_iterators.py
iotccsdk/ipcprovider.py
iotccsdk/logger.conf
iotccsdk-0.1.4.dist-info/LICENSE.txt
iotccsdk-0.1.4.dist-info/METADATA
iotccsdk-0.1.4.dist-info/WHEEL
iotccsdk-0.1.4.dist-info/top_level.txt
iotccsdk-0.1.4.dist-info/RECORD
