Metadata-Version: 2.1
Name: iotccsdk
Version: 0.1.4
Summary: SDK in Python for interacting with the Vision AI DevKit. See https://aka.ms/visionaidevkit
Home-page: https://github.com/microsoft/vision-ai-developer-kit
License: BSD-3-Clause
Project-URL: Vision AI DevKit Page, https://azure.github.io/Vision-AI-DevKit-Pages/
Project-URL: Get Started, https://azure.github.io/Vision-AI-DevKit-Pages/docs/Get_Started/
Keywords: iot,ai,camera
Platform: UNKNOWN
Classifier: Development Status :: 4 - Beta
Classifier: Framework :: IPython
Classifier: Intended Audience :: Developers
Classifier: Topic :: Multimedia :: Graphics :: Capture :: Digital Camera
Classifier: Topic :: Multimedia :: Video
Classifier: Topic :: Scientific/Engineering :: Artificial Intelligence
Classifier: Topic :: Software Development
Classifier: Programming Language :: Python :: 3.5
Requires-Python: ~=3.5
Requires-Dist: pip (>=9.0.0)
Requires-Dist: requests
Requires-Dist: setuptools-git
Requires-Dist: websocket-client
